setup.py
python_ridc.egg-info/PKG-INFO
python_ridc.egg-info/SOURCES.txt
python_ridc.egg-info/dependency_links.txt
python_ridc.egg-info/top_level.txt
ridc/__init__.py
ridc/twisted_connector.py