Metadata-Version: 1.1
Name: python-ridc
Version: 0.1
Summary: Python connector for Ridc
Home-page: UNKNOWN
Author: Rob Britton
Author-email: rob@robbritton.com
License: UNKNOWN
Platform: UNKNOWN
Classifier: Programming Language :: Python
Classifier: License :: OSI Approved :: MIT License
Classifier: Development Status :: 3 - Alpha
Classifier: Intended Audience :: Developers
Classifier: Topic :: Database :: Database Engines/Servers
